pybeoplay/__init__.py
pybeoplay/const.py
pybeoplay-2.8.2.dist-info/licenses/LICENSE
pybeoplay-2.8.2.dist-info/METADATA
pybeoplay-2.8.2.dist-info/WHEEL
pybeoplay-2.8.2.dist-info/top_level.txt
pybeoplay-2.8.2.dist-info/RECORD
