Metadata-Version: 2.4
Name: pybeoplay
Version: 2.8.2
Summary: BeoPlay API for Python
Home-page: https://github.com/giachello/pybeoplay
Download-URL: https://github.com/giachello/pybeoplay/tarball/2.8.2
Author: Giovanni Iachello
Author-email: giovanni.iachello@gmail.com
License: MIT License
Keywords: beoplay,pybeoplay,B&O,Bang & Olufsen
Platform: any
Classifier: Intended Audience :: Developers
Classifier: License :: OSI Approved :: MIT License
Classifier: Operating System :: OS Independent
Classifier: Programming Language :: Python :: 3.9
License-File: LICENSE
Dynamic: author
Dynamic: author-email
Dynamic: classifier
Dynamic: description
Dynamic: description-content-type
Dynamic: download-url
Dynamic: home-page
Dynamic: keywords
Dynamic: license
Dynamic: license-file
Dynamic: platform
Dynamic: summary
